docs/__init__.py
docs/source/__init__.py
docs/source/conf.py
neodroidagent/__init__.py
neodroidagent/agents/__init__.py
neodroidagent/agents/agent.py
neodroidagent/agents/random_agent.py
neodroidagent/agents/exclude/__init__.py
neodroidagent/agents/exclude/dppo_agent.py
neodroidagent/agents/exclude/recurrent_agent.py
neodroidagent/agents/exclude/trpo_agent.py
neodroidagent/agents/exclude/behavioural_cloning/__init__.py
neodroidagent/agents/exclude/behavioural_cloning/bc.py
neodroidagent/agents/exclude/behavioural_cloning/imitation_agent.py
neodroidagent/agents/exclude/evolutionary/__init__.py
neodroidagent/agents/exclude/evolutionary/cma_agent.py
neodroidagent/agents/exclude/evolutionary/evo_agent.py
neodroidagent/agents/exclude/evolutionary/ga_agent.py
neodroidagent/agents/exclude/model_based/__init__.py
neodroidagent/agents/exclude/model_based/curiousity_agent.py
neodroidagent/agents/exclude/model_based/dynaq_agent.py
neodroidagent/agents/exclude/model_based/world_model_agent.py
neodroidagent/agents/numpy_agents/__init__.py
neodroidagent/agents/numpy_agents/numpy_agent.py
neodroidagent/agents/numpy_agents/evolutionary/__init__.py
neodroidagent/agents/numpy_agents/evolutionary/cma_agent_tf.py
neodroidagent/agents/numpy_agents/evolutionary/exclude/__init__.py
neodroidagent/agents/numpy_agents/evolutionary/exclude/akro/__init__.py
neodroidagent/agents/numpy_agents/evolutionary/exclude/akro/box.py
neodroidagent/agents/numpy_agents/evolutionary/exclude/akro/dict.py
neodroidagent/agents/numpy_agents/evolutionary/exclude/akro/discrete.py
neodroidagent/agents/numpy_agents/evolutionary/exclude/akro/image.py
neodroidagent/agents/numpy_agents/evolutionary/exclude/akro/requires.py
neodroidagent/agents/numpy_agents/evolutionary/exclude/akro/space.py
neodroidagent/agents/numpy_agents/evolutionary/exclude/akro/tuple.py
neodroidagent/agents/numpy_agents/evolutionary/get_rid/__init__.py
neodroidagent/agents/numpy_agents/evolutionary/get_rid/local_runner.py
NeodroidAgent-0.4.8.dist-info/LICENSE.md
NeodroidAgent-0.4.8.dist-info/METADATA
NeodroidAgent-0.4.8.dist-info/WHEEL
NeodroidAgent-0.4.8.dist-info/entry_points.txt
NeodroidAgent-0.4.8.dist-info/top_level.txt
NeodroidAgent-0.4.8.dist-info/RECORD
